pydory.cpython-311-darwin.so
pydory-1.1.137.dist-info/METADATA
pydory-1.1.137.dist-info/WHEEL
pydory-1.1.137.dist-info/top_level.txt
pydory-1.1.137.dist-info/RECORD
