Metadata-Version: 2.1
Name: pydory
Version: 1.1.137
Summary: Python interface for Dory
Author: Manu Aggarwal
Author-email: manu.aggarwal@nih.gov
Requires-Python: >=3
